[
    {
        "model": "securelifeapi.human",
        "pk": 1,
        "fields": {
            "creator": 1,
            "name": "Josh"
        }
    },
    {
        "model": "securelifeapi.human",
        "pk": 2,
        "fields": {
            "creator": 1,
            "name": "Angel"
        }
    },
    {
        "model": "securelifeapi.human",
        "pk": 3,
        "fields": {
            "creator": 1,
            "name": "Katie"
        }
    },
    {
        "model": "securelifeapi.human",
        "pk": 4,
        "fields": {
            "creator": 1,
            "name": "Seth"
        }
    },
    {
        "model": "securelifeapi.human",
        "pk": 5,
        "fields": {
            "creator": 1,
            "name": "Hannah"
        }
    },
    {
        "model": "securelifeapi.human",
        "pk": 6,
        "fields": {
            "creator": 1,
            "name": "Rich (Poppers)"
        }
    },
    {
        "model": "securelifeapi.human",
        "pk": 7,
        "fields": {
            "creator": 1,
            "name": "Tammy (Grammy)"
        }
    }
]
